<metadata xml:lang="en"><Esri><CreaDate>20120518</CreaDate><CreaTime>09105900</CreaTime><SyncOnce>FALSE</SyncOnce><SyncDate>20090225</SyncDate><SyncTime>08192000</SyncTime><ModDate>20090225</ModDate><ModTime>08193800</ModTime><DataProperties><lineage><Process ToolSource="C:\Program Files\ArcGIS\Desktop10.0\ArcToolbox\Toolboxes\Data Management Tools.tbx\CalculateField" Date="20120517" Time="115631" Name="" export="">CalculateField ca_50mwind WPC [GRIDCODE] VB #</Process></lineage></DataProperties><ArcGISFormat>1.0</ArcGISFormat><ArcGISProfile>ItemDescription</ArcGISProfile></Esri><idinfo><native Sync="TRUE">Microsoft Windows XP Version 5.1 (Build 2600) Service Pack 3; ESRI ArcCatalog 9.3.0.1770</native><descript><langdata Sync="TRUE">en</langdata><abstract>Annual average wind resource potential of California at a 50 meter height.</abstract><purpose>Provide information on the wind resource development potential within California.</purpose><supplinf>This data set was produced by TrueWind Solutions using their Mesomap system and historical weather data, under funding from the California Energy Commission.  It has been validated by NREL and wind energy meteorological consultants.  This shapefile was generated from a raster dataset with a 200 m resolution, in a UTM zone 11, datum WGS 84 projection system. 

On-site measurement is strongly recommended before siting potential wind farm developments.</supplinf></descript><citation><citeinfo><origin>TrueWind Solutions/NREL</origin><pubdate>January, 2003</pubdate><title Sync="TRUE">ca_50mwind</title><ftname Sync="TRUE">ca_50mwind</ftname><geoform Sync="TRUE">vector digital data</geoform><onlink Sync="TRUE">\\PGRAY-12799S\C$\Documents and Settings\PGray\Desktop\GISdatazipfiles\Wind_Data\extracted_wind\ca_50mwind.shp</onlink><othercit>The wind power resource estimates were produced by TrueWind Solutions using their MesoMap system and historical weather data under contract to Wind Powering America/NREL.  This map has been validated with available surface data by NREL and wind energy meteorological consultants.</othercit></citeinfo></citation><timeperd><current>publication date</current><timeinfo><sngdate><caldate>January, 2003</caldate></sngdate></timeinfo></timeperd><status><progress>Complete</progress><update>None planned</update></status><spdom><bounding><westbc Sync="TRUE">-124.643293</westbc><eastbc Sync="TRUE">-114.130598</eastbc><northbc Sync="TRUE">42.010057</northbc><southbc Sync="TRUE">32.355032</southbc></bounding><lboundng><leftbc Sync="TRUE">-124.643293</leftbc><rightbc Sync="TRUE">-114.130598</rightbc><bottombc Sync="TRUE">32.355032</bottombc><topbc Sync="TRUE">42.010057</topbc></lboundng></spdom><keywords><theme><themekt>REQUIRED: Reference to a formally registered thesaurus or a similar authoritative source of theme keywords.</themekt><themekey>Wind potential, wind resource</themekey></theme></keywords><accconst>None</accconst><natvform Sync="TRUE">Shapefile</natvform><useconst>This GIS data was developed by the National Renewable Energy Laboratory ("NREL"), which is operated by the Alliance for Sustainable Energy, LLC  for the U.S. Department of Energy ("DOE"). The user is granted the right, without any fee or cost, to use, copy, modify, alter, enhance and distribute this data for any purpose whatsoever, provided that this entire notice appears in all copies of the data. Further, the user of this data agrees to credit NREL in any publications or software that incorporate or use the data. 

Access to and use of the GIS data shall further impose the following obligations on the User. The names DOE/NREL may not be used in any advertising or publicity to endorse or promote any product or commercial entity using or incorporating the GIS data unless specific written authorization is obtained from DOE/NREL. The User also understands that DOE/NREL shall not be obligated to provide updates, support, consulting, training or assistance of any kind whatsoever with regard to the use of the GIS data. 

THE GIS DATA IS PROVIDED "AS IS" AND ANY EXPRESS OR IMPLIED WARRANTIES, INCLUDING BUT NOT LIMITED TO, THE IMPLIED WARRANTIES OF MERCHANTABILITY AND FITNESS FOR A PARTICULAR PURPOSE ARE DISCLAIMED. IN NO EVENT SHALL DOE/NREL BE LIABLE FOR ANY SPECIAL, INDIRECT OR CONSEQUENTIAL DAMAGES OR ANY DAMAGES WHATSOEVER, INCLUDING BUT NOT LIMITED TO CLAIMS ASSOCIATED WITH THE LOSS OF DATA OR PROFITS, WHICH MAY RESULT FROM AN ACTION IN CONTRACT, NEGLIGENCE OR OTHER TORTIOUS CLAIM THAT ARISES OUT OF OR IN CONNECTION WITH THE ACCESS OR USE OF THE GIS DATA. 

The User acknowledges that access to the GIS data is subject to U.S. Export laws and regulations and any use or transfer of the GIS data must be authorized under those regulations. The User shall not use, distribute, transfer, or transmit GIS data or any products incorporating the GIS data except in compliance with U.S. export regulations. If requested by DOE/NREL, the User agrees to sign written assurances and other export-related documentation as may be required to comply with U.S. export regulations.</useconst><ptcontac><cntinfo><cntperp><cntper>Donna Heimiller</cntper><cntorg>National Renewable Energy Laboratory</cntorg></cntperp><cntpos>Scientist II (GIS)</cntpos><cntaddr><addrtype>mailing address</addrtype><address>1617 Cole Blvd</address><city>Golden</city><state>CO</state><postal>80401</postal><country>USA</country></cntaddr><cntvoice>303-384-7098</cntvoice><cntfax>303-384-6901</cntfax><cntemail>donna_heimiller@nrel.gov</cntemail></cntinfo></ptcontac></idinfo><metainfo><langmeta Sync="TRUE">en</langmeta><metstdn Sync="TRUE">FGDC Content Standards for Digital Geospatial Metadata</metstdn><metstdv Sync="TRUE">FGDC-STD-001-1998</metstdv><mettc Sync="TRUE">local time</mettc><metc><cntinfo><cntaddr><addrtype>mailing address</addrtype><city>Golden</city><state>CO</state><postal>80401</postal><address>1617 Cole Blvd</address><country>USA</country></cntaddr><cntvoice>303-384-7098</cntvoice><cntperp><cntper>Donna Heimiller</cntper><cntorg>National Renewable Energy Laboratory</cntorg></cntperp><cntpos>Scientist II (GIS)</cntpos><cntfax>303-384-6901</cntfax><cntemail>donna_heimiller@nrel.gov</cntemail></cntinfo></metc><metd Sync="TRUE">20090225</metd><metextns><onlink Sync="TRUE">http://www.esri.com/metadata/esriprof80.html</onlink><metprof Sync="TRUE">ESRI Metadata Profile</metprof></metextns></metainfo><spdoinfo><direct Sync="TRUE">Vector</direct><ptvctinf><esriterm Name="ca_50mwind"><efeatyp Sync="TRUE">Simple</efeatyp><efeageom Sync="TRUE">Polygon</efeageom><esritopo Sync="TRUE">FALSE</esritopo><efeacnt Sync="TRUE">197434</efeacnt><spindex Sync="TRUE">FALSE</spindex><linrefer Sync="TRUE">FALSE</linrefer></esriterm><sdtsterm Name="ca_50mwind"><sdtstype Sync="TRUE">G-polygon</sdtstype><ptvctcnt Sync="TRUE">197434</ptvctcnt></sdtsterm></ptvctinf></spdoinfo><spref><horizsys><cordsysn><geogcsn Sync="TRUE">GCS_WGS_1984</geogcsn></cordsysn><geograph><geogunit Sync="TRUE">Decimal degrees</geogunit><latres Sync="TRUE">0.000000</latres><longres Sync="TRUE">0.000000</longres></geograph><geodetic><horizdn Sync="TRUE">D_WGS_1984</horizdn><ellips Sync="TRUE">WGS_1984</ellips><semiaxis Sync="TRUE">6378137.000000</semiaxis><denflat Sync="TRUE">298.257224</denflat></geodetic></horizsys></spref><eainfo><detailed Name="ca_50mwind"><enttyp><enttypl Sync="TRUE">ca_50mwind</enttypl><enttypt Sync="TRUE">Feature Class</enttypt><enttypc Sync="TRUE">197434</enttypc></enttyp><attr><attrlabl Sync="TRUE">FID</attrlabl><attalias Sync="TRUE">FID</attalias><attrtype Sync="TRUE">OID</attrtype><attwidth Sync="TRUE">4</attwidth><atprecis Sync="TRUE">0</atprecis><attscale Sync="TRUE">0</attscale><attrdef Sync="TRUE">Internal feature number.</attrdef><attrdefs Sync="TRUE">ESRI</attrdefs><attrdomv><udom Sync="TRUE">Sequential unique whole numbers that are automatically generated.</udom></attrdomv></attr><attr><attrlabl Sync="TRUE">Shape</attrlabl><attalias Sync="TRUE">Shape</attalias><attrtype Sync="TRUE">Geometry</attrtype><attwidth Sync="TRUE">0</attwidth><atprecis Sync="TRUE">0</atprecis><attscale Sync="TRUE">0</attscale><attrdef Sync="TRUE">Feature geometry.</attrdef><attrdefs Sync="TRUE">ESRI</attrdefs><attrdomv><udom Sync="TRUE">Coordinates defining the features.</udom></attrdomv></attr><attr><attrlabl Sync="TRUE">ID</attrlabl><attalias Sync="TRUE">ID</attalias><attrtype Sync="TRUE">Number</attrtype><attwidth Sync="TRUE">10</attwidth><attrdef>Feature ID</attrdef></attr><attr><attrlabl Sync="TRUE">GRIDCODE</attrlabl><attalias Sync="TRUE">GRIDCODE</attalias><attrtype Sync="TRUE">Number</attrtype><attwidth Sync="TRUE">10</attwidth></attr></detailed><overview><dsoverv>Annual average wind resource potential of California at a 50 meter height.</dsoverv><eaover>Wind power class is an indicator of likely resource strength, with a higher wind power class representing higher wind resource levels.  The following classification information is for utility-scale applications at a 50 meter height.

Power   Resource   50 m Wind Power
Class    Potential    Density (W/m2)
1          Poor                0 - 200
2          Marginal       200 - 300
3          Fair              300 - 400
4          Good            400 - 500
5          Excellent       500 - 600
6          Outstanding  600 - 800
7          Superb             &gt; 800</eaover></overview></eainfo><distinfo><stdorder><digform><digtinfo><transize Sync="TRUE">50.055</transize><dssize Sync="TRUE">50.055</dssize></digtinfo></digform></stdorder><distliab>This GIS data was developed by the National Renewable Energy Laboratory ("NREL"), which is operated by the Alliance for Sustainable Energy, LLC for the U.S. Department of Energy ("DOE"). The user is granted the right, without any fee or cost, to use, copy, modify, alter, enhance and distribute this data for any purpose whatsoever, provided that this entire notice appears in all copies of the data. Further, the user of this data agrees to credit NREL in any publications or software that incorporate or use the data. 

Access to and use of the GIS data shall further impose the following obligations on the User. The names DOE/NREL may not be used in any advertising or publicity to endorse or promote any product or commercial entity using or incorporating the GIS data unless specific written authorization is obtained from DOE/NREL. The User also understands that DOE/NREL shall not be obligated to provide updates, support, consulting, training or assistance of any kind whatsoever with regard to the use of the GIS data. 

THE GIS DATA IS PROVIDED "AS IS" AND ANY EXPRESS OR IMPLIED WARRANTIES, INCLUDING BUT NOT LIMITED TO, THE IMPLIED WARRANTIES OF MERCHANTABILITY AND FITNESS FOR A PARTICULAR PURPOSE ARE DISCLAIMED. IN NO EVENT SHALL DOE/NREL BE LIABLE FOR ANY SPECIAL, INDIRECT OR CONSEQUENTIAL DAMAGES OR ANY DAMAGES WHATSOEVER, INCLUDING BUT NOT LIMITED TO CLAIMS ASSOCIATED WITH THE LOSS OF DATA OR PROFITS, WHICH MAY RESULT FROM AN ACTION IN CONTRACT, NEGLIGENCE OR OTHER TORTIOUS CLAIM THAT ARISES OUT OF OR IN CONNECTION WITH THE ACCESS OR USE OF THE GIS DATA. 

The User acknowledges that access to the GIS data is subject to U.S. Export laws and regulations and any use or transfer of the GIS data must be authorized under those regulations. The User shall not use, distribute, transfer, or transmit GIS data or any products incorporating the GIS data except in compliance with U.S. export regulations. If requested by DOE/NREL, the User agrees to sign written assurances and other export-related documentation as may be required to comply with U.S. export regulations.</distliab><resdesc Sync="TRUE">Downloadable Data</resdesc></distinfo><dataIdInfo><envirDesc Sync="TRUE">Microsoft Windows XP Version 5.1 (Build 2600) Service Pack 3; ESRI ArcCatalog 9.3.0.1770</envirDesc><dataLang><languageCode Sync="TRUE" value="en"/></dataLang><idCitation><resTitle Sync="TRUE">ca_50mwind</resTitle><presForm><PresFormCd Sync="TRUE" value="005"/></presForm></idCitation><spatRpType><SpatRepTypCd Sync="TRUE" value="001"/></spatRpType><dataExt><geoEle><GeoBndBox esriExtentType="native"><westBL Sync="TRUE">-124.643293</westBL><eastBL Sync="TRUE">-114.130598</eastBL><northBL Sync="TRUE">42.010057</northBL><southBL Sync="TRUE">32.355032</southBL><exTypeCode Sync="TRUE">1</exTypeCode></GeoBndBox></geoEle></dataExt><geoBox esriExtentType="decdegrees"><westBL Sync="TRUE">-124.643293</westBL><eastBL Sync="TRUE">-114.130598</eastBL><northBL Sync="TRUE">42.010057</northBL><southBL Sync="TRUE">32.355032</southBL><exTypeCode Sync="TRUE">1</exTypeCode></geoBox><idPurp>Provide information on the wind resource development potential within California.</idPurp><idAbs>&lt;DIV STYLE="text-align:Left;"&gt;&lt;DIV&gt;&lt;P&gt;&lt;SPAN&gt;Annual average wind resource potential of California at a 50 meter height.&lt;/SPAN&gt;&lt;/P&gt;&lt;/DIV&gt;&lt;/DIV&gt;</idAbs><searchKeys><keyword>Wind potential</keyword><keyword>wind resource</keyword></searchKeys></dataIdInfo><mdLang><languageCode Sync="TRUE" value="en"/></mdLang><mdStanName Sync="TRUE">ISO 19115 Geographic Information - Metadata</mdStanName><mdStanVer Sync="TRUE">DIS_ESRI1.0</mdStanVer><mdChar><CharSetCd Sync="TRUE" value="004"/></mdChar><mdHrLv><ScopeCd Sync="TRUE" value="005"/></mdHrLv><mdHrLvName Sync="TRUE">dataset</mdHrLvName><distInfo><distributor><distorTran><onLineSrc><orDesc Sync="TRUE">002</orDesc><linkage Sync="TRUE">file://\\PGRAY-12799S\C$\Documents and Settings\PGray\Desktop\GISdatazipfiles\Wind_Data\extracted_wind\ca_50mwind.shp</linkage><protocol Sync="TRUE">Local Area Network</protocol></onLineSrc><transSize Sync="TRUE">50.055</transSize></distorTran><distorFormat><formatName Sync="TRUE">Shapefile</formatName></distorFormat></distributor></distInfo><refSysInfo><RefSystem><refSysID><identCode Sync="TRUE">GCS_WGS_1984</identCode></refSysID></RefSystem></refSysInfo><spatRepInfo><VectSpatRep><topLvl><TopoLevCd Sync="TRUE" value="001"/></topLvl><geometObjs Name="ca_50mwind"><geoObjTyp><GeoObjTypCd Sync="TRUE" value="001"/></geoObjTyp><geoObjCnt Sync="TRUE">197434</geoObjCnt></geometObjs></VectSpatRep></spatRepInfo><mdDateSt Sync="TRUE">20090225</mdDateSt></metadata>
